bookkeeping/__init__.py
bookkeeping/analysis/__init__.py
bookkeeping/analysis/analytics.py
bookkeeping/analysis/budget.py
bookkeeping/analysis/summary.py
bookkeeping/management/__init__.py
bookkeeping/management/book.py
bookkeeping/management/negative_amount_error.py
bookkeeping/management/transaction.py
bookkeeping-0.0.8.dist-info/LICENSE.txt
bookkeeping-0.0.8.dist-info/METADATA
bookkeeping-0.0.8.dist-info/WHEEL
bookkeeping-0.0.8.dist-info/top_level.txt
bookkeeping-0.0.8.dist-info/RECORD
