Metadata-Version: 2.1
Name: bookkeeping
Version: 0.0.8
Summary: A bookkeeping package
Author-email: Jinxin Wang <jinxindata@gmail.com>, Nan Tang <dejaytang@gmail.com>
Project-URL: Homepage, https://github.com/dejaytang/project-step-3-group6
Project-URL: Issues, https://github.com/dejaytang/project-step-3-group6/issues
Classifier: Programming Language :: Python :: 3
Classifier: License :: OSI Approved :: MIT License
Classifier: Operating System :: OS Independent
Requires-Python: >=3.8
License-File: LICENSE.txt
